gitshoes/__init__.py
gitshoes/reporter.py
gitshoes-1.2.0.dist-info/COPYING
gitshoes-1.2.0.dist-info/METADATA
gitshoes-1.2.0.dist-info/WHEEL
gitshoes-1.2.0.dist-info/entry_points.txt
gitshoes-1.2.0.dist-info/top_level.txt
gitshoes-1.2.0.dist-info/RECORD
